rydia/__init__.py
rydia/rydia.cpython-310-darwin.so
rydia_core-0.1.0.dist-info/METADATA
rydia_core-0.1.0.dist-info/WHEEL
rydia_core-0.1.0.dist-info/licenses/LICENSE
rydia_core-0.1.0.dist-info/RECORD
