Metadata-Version: 2.4
Name: rydia-core
Version: 0.1.0
Classifier: Programming Language :: Rust
Classifier: Programming Language :: Python :: 3
Classifier: Programming Language :: Python :: 3 :: Only
Classifier: Programming Language :: Python :: Implementation :: CPython
Classifier: Operating System :: OS Independent
Classifier: Topic :: Multimedia :: Sound/Audio
Classifier: Topic :: Software Development :: Libraries
License-File: LICENSE
Summary: A Rust-based UGen DSP library for offline audio experimentation, with Python bindings
Author-email: inaba1115 <inaba1115@gmail.com>
Requires-Python: >=3.10
